dyndesign/__init__.py
dyndesign/classbuilder/class_builder.py
dyndesign/classbuilder/class_configuration_manager.py
dyndesign/classbuilder/class_configuration_unit.py
dyndesign/classbuilder/class_importer.py
dyndesign/classbuilder/class_storage.py
dyndesign/classbuilder/component_class_builder.py
dyndesign/classbuilder/dependency_configuration.py
dyndesign/classbuilder/dynamic_configuration.py
dyndesign/classbuilder/exposed_class_config.py
dyndesign/classbuilder/parent_class_builder.py
dyndesign/classbuilder/settings.py
dyndesign/classmerger.py
dyndesign/dyninherit/dyninherit.py
dyndesign/dyninherit/dyninherit_base.py
dyndesign/dyninherit/dyninherit_locked_instances.py
dyndesign/dynloader.py
dyndesign/dynmethod.py
dyndesign/exceptions.py
dyndesign/singletonmeta.py
dyndesign/utils/inspector.py
dyndesign/utils/misc.py
dyndesign/utils/signature.py
dyndesign-1.1.0.dist-info/LICENSE.txt
dyndesign-1.1.0.dist-info/METADATA
dyndesign-1.1.0.dist-info/WHEEL
dyndesign-1.1.0.dist-info/RECORD
