Metadata-Version: 2.1
Name: dyndesign
Version: 1.1.0
Summary: Toolset for Dynamic Design in Python.
Home-page: https://github.com/amarula/dyndesign
License: MIT
Keywords: design,dynamic,decorator,inheritance
Author: Patrizio Gelosi
Author-email: patrizio.gelosi@amarulasolutions.com
Maintainer: Patrizio Gelosi
Maintainer-email: patrizio.gelosi@amarulasolutions.com
Requires-Python: >=3.8,<4.0
Classifier: Environment :: Console
Classifier: Intended Audience :: Developers
Classifier: License :: OSI Approved :: MIT License
Classifier: Operating System :: OS Independent
Classifier: Programming Language :: Python
Classifier: Programming Language :: Python :: 3
Classifier: Programming Language :: Python :: 3.8
Classifier: Programming Language :: Python :: 3.9
Classifier: Programming Language :: Python :: 3.10
Classifier: Programming Language :: Python :: 3.11
Classifier: Topic :: Software Development :: Build Tools
Classifier: Topic :: Software Development :: Libraries :: Python Modules
Project-URL: Repository, https://github.com/amarula/dyndesign
